perftool/__init__.py
perftool/__main__.py
perftool/manage.py
perftool/executer/__init__.py
perftool/executer/executer.py
perftool/executer/listener.py
perftool/ext/__init__.py
perftool/ext/executer.py
perftool/ext/listener.py
perftool-0.1.4.dist-info/DESCRIPTION.rst
perftool-0.1.4.dist-info/METADATA
perftool-0.1.4.dist-info/RECORD
perftool-0.1.4.dist-info/WHEEL
perftool-0.1.4.dist-info/metadata.json
perftool-0.1.4.dist-info/top_level.txt
