Metadata-Version: 2.0
Name: perftool
Version: 0.1.4
Summary: The Performance Tool
Home-page: https://github.com/Yajan/Perftool.git
Author: Yajana
Author-email: yajananrao@gmail.com
License: Apache License
Platform: UNKNOWN
